kiarina/currency/__init__.py
kiarina/currency/py.typed
kiarina/currency/currency_code/__init__.py
kiarina/currency/currency_code/_types/__init__.py
kiarina/currency/currency_code/_types/currency_code.py
kiarina/currency/currency_error/__init__.py
kiarina/currency/currency_error/_exceptions/__init__.py
kiarina/currency/currency_error/_exceptions/currency_error.py
kiarina/currency/currency_error/_exceptions/exchange_rate_not_found_error.py
kiarina/currency/rate/__init__.py
kiarina/currency/rate/_helpers/__init__.py
kiarina/currency/rate/_helpers/get_exchange_rate.py
kiarina/currency/rate/_types/__init__.py
kiarina/currency/rate/_types/rate_options.py
kiarina/currency/rate_provider/__init__.py
kiarina/currency/rate_provider/_settings.py
kiarina/currency/rate_provider/_helpers/__init__.py
kiarina/currency/rate_provider/_helpers/create_rate_provider.py
kiarina/currency/rate_provider/_models/__init__.py
kiarina/currency/rate_provider/_models/base_rate_provider.py
kiarina/currency/rate_provider/_types/__init__.py
kiarina/currency/rate_provider/_types/rate_provider.py
kiarina/currency/rate_provider/_types/rate_provider_name.py
kiarina/currency/rate_provider_impl/__init__.py
kiarina/currency/rate_provider_impl/frankfurter/__init__.py
kiarina/currency/rate_provider_impl/frankfurter/_settings.py
kiarina/currency/rate_provider_impl/frankfurter/_models/__init__.py
kiarina/currency/rate_provider_impl/frankfurter/_models/frankfurter_rate_provider.py
kiarina/currency/rate_provider_impl/static/__init__.py
kiarina/currency/rate_provider_impl/static/_settings.py
kiarina/currency/rate_provider_impl/static/_models/__init__.py
kiarina/currency/rate_provider_impl/static/_models/static_rate_provider.py
kiarina/currency/system_currency/__init__.py
kiarina/currency/system_currency/_helpers/__init__.py
kiarina/currency/system_currency/_helpers/get_system_currency.py
kiarina_currency-1.35.0.dist-info/METADATA
kiarina_currency-1.35.0.dist-info/WHEEL
kiarina_currency-1.35.0.dist-info/top_level.txt
kiarina_currency-1.35.0.dist-info/RECORD
